AMSC/AMSC_Object.py
AMSC/__init__.py
AMSC/_amsc.cpython-39-darwin.so
AMSC/amsc.py
crow_modules/__init__.py
crow_modules/_distribution1D.cpython-39-darwin.so
crow_modules/_interpolationND.cpython-39-darwin.so
crow_modules/_randomENG.cpython-39-darwin.so
crow_modules/distribution1D.py
crow_modules/interpolationND.py
crow_modules/randomENG.py
ravenframework/Application.py
ravenframework/ClassProperty.py
ravenframework/CodeInterfaceBaseClass.py
ravenframework/CsvLoader.py
ravenframework/CustomCommandExecuter.py
ravenframework/Distributions.py
ravenframework/Distributions1D.py
ravenframework/DistributionsND.py
ravenframework/Driver.py
ravenframework/EntityFactoryBase.py
ravenframework/Files.py
ravenframework/Functions.py
ravenframework/GridEntities.py
ravenframework/IndexSets.py
ravenframework/Interaction.py
ravenframework/JobHandler.py
ravenframework/MessageHandler.py
ravenframework/MetricDistributor.py
ravenframework/OrthoPolynomials.py
ravenframework/PluginManager.py
ravenframework/Quadratures.py
ravenframework/ROMExternal.py
ravenframework/Simulation.py
ravenframework/VariableGroups.py
ravenframework/__init__.py
ravenframework/h5py_interface_creator.py
ravenframework/raven_qsub_command.py
ravenframework/unSupervisedLearning.py
ravenframework/BaseClasses/Assembler.py
ravenframework/BaseClasses/BaseEntity.py
ravenframework/BaseClasses/BaseInterface.py
ravenframework/BaseClasses/BaseType.py
ravenframework/BaseClasses/InputDataUser.py
ravenframework/BaseClasses/MessageUser.py
ravenframework/BaseClasses/PluginReadyEntity.py
ravenframework/BaseClasses/__init__.py
ravenframework/CodeInterfaceClasses/Factory.py
ravenframework/CodeInterfaceClasses/__init__.py
ravenframework/CodeInterfaceClasses/Abce/AbceCodeInterface.py
ravenframework/CodeInterfaceClasses/Abce/__init__.py
ravenframework/CodeInterfaceClasses/AccelerateCFD/AccelerateCFD.py
ravenframework/CodeInterfaceClasses/AccelerateCFD/__init__.py
ravenframework/CodeInterfaceClasses/AccelerateCFD/OpenFoamPP/__init__.py
raven_framework-3.1.dist-info/LICENSE.txt
raven_framework-3.1.dist-info/METADATA
raven_framework-3.1.dist-info/NOTICE.txt
raven_framework-3.1.dist-info/WHEEL
raven_framework-3.1.dist-info/entry_points.txt
raven_framework-3.1.dist-info/top_level.txt
raven_framework-3.1.dist-info/RECORD
