Metadata-Version: 2.1
Name: raven_framework
Version: 3.1
Summary: RAVEN (Risk Analysis Virtual Environment) is designed to perform parametric and probabilistic analysis based on the response of complex system codes. RAVEN C++ dependenciences including a library for computing the Approximate Morse-Smale Complex (AMSC) and Crow probability tools
Home-page: https://raven.inl.gov/
Classifier: Programming Language :: Python :: 3
License-File: LICENSE.txt
License-File: NOTICE.txt
Requires-Dist: netcdf4 ==1.6.*
Requires-Dist: cloudpickle ==2.2.*
Requires-Dist: grpcio
Requires-Dist: xarray ==2023.*
Requires-Dist: dask[complete]
Requires-Dist: mamba
Requires-Dist: numdifftools ==0.9.*
Requires-Dist: ray[default] ==2.6.*
Requires-Dist: lxml
Requires-Dist: smt
Requires-Dist: python-sensors
Requires-Dist: tensorflow ==2.13.*
Requires-Dist: numpy ==1.22.*
Requires-Dist: pandas
Requires-Dist: statsforecast
Requires-Dist: pyDOE3
Requires-Dist: pylint
Requires-Dist: matplotlib ==3.5.*
Requires-Dist: h5py
Requires-Dist: scipy ==1.9.*
Requires-Dist: coverage
Requires-Dist: xmlschema
Requires-Dist: imageio ==2.22.*
Requires-Dist: scikit-learn ==1.0.*
Requires-Dist: psutil
Requires-Dist: setuptools ==69.*
Requires-Dist: statsmodels ==0.13.*
Requires-Dist: importlib-metadata
